projectutils/__init__.py
projectutils/config.py
projectutils/init.py
projectutils-1.2.dist-info/LICENSE
projectutils-1.2.dist-info/METADATA
projectutils-1.2.dist-info/WHEEL
projectutils-1.2.dist-info/top_level.txt
projectutils-1.2.dist-info/RECORD
