Metadata-Version: 2.1
Name: projectutils
Version: 1.2
Summary: A small collections of modular components useful in other projects.
Home-page: https://github.com/manuelpepe/projectutils
Author: Manuel Pepe
Author-email: manuelpepe-dev@outlook.com.ar
License: UNKNOWN
Platform: UNKNOWN
License-File: LICENSE
Requires-Dist: python-dotenv
Requires-Dist: rst (==0.1)
Provides-Extra: toml
Requires-Dist: toml ; extra == 'toml'
